zdppy_consul/__init__.py
zdppy_consul/consul.py
zdppy_consul-0.1.1.dist-info/WHEEL
zdppy_consul-0.1.1.dist-info/METADATA
zdppy_consul-0.1.1.dist-info/RECORD
